psya/__init__.py
psya/__main__.py
psya/app.py
psya/brain.py
psya/dicts.py
psya/ht.py
psya/room.py
psya/shell.py
psya/space.py
psya/the.py
psya/wire.py
psya/mut/__init__.py
psya/mut/bridge.py
psya/mut/dict.py
psya/mut/evaluation.py
psya/mut/events.py
psya/mut/mutation.py
psya/mut/observer.py
psya/mut/ref.py
psya/statics/index.html
psya/statics/js/main.js
psya-0.0.0.dist-info/METADATA
psya-0.0.0.dist-info/WHEEL
psya-0.0.0.dist-info/RECORD
