Metadata-Version: 2.3
Name: psya
Version: 0.0.0
Summary: live python playground
Project-URL: Homepage, https://github.com/queerviolet/psya
Project-URL: Issues, https://github.com/queerviolet/psya/issues
Author-email: ashi <i@ashi.io>
Classifier: Development Status :: 2 - Pre-Alpha
Classifier: License :: OSI Approved :: MIT License
Classifier: Operating System :: OS Independent
Classifier: Programming Language :: Python :: 3
Classifier: Programming Language :: Python :: 3.9
Classifier: Programming Language :: Python :: 3.10
Classifier: Programming Language :: Python :: 3.11
Requires-Python: >=3.8
Requires-Dist: starlette
Requires-Dist: uvicorn
